{
    "id": 32066,
    "url": "https://vc.ru/finance/32066-rosteh-zapustit-venchurnyy-fond-na-500-mln-rubley-dlya-investiciy-v-it-proekty",
    "dateRFC": "Fri, 19 Jan 2018 14:45:33 +0300",
    "date": 1516362333,
    "title": "«Ростех» запустит венчурный фонд на 500 млн рублей для инвестиций в ИТ-проекты",
    "intro": "Госкорпорации инвестируют в стартапы по поручению Владимира Путина.",
    "text": "Госкорпорации инвестируют в стартапы по поручению Владимира Путина. Госкорпорация «Ростех» создаст венчурный фонд объёмом 500 млн рублей для инвестиций в высокотехнологичные проекты в сфере ИТ и электроники. Об этом пишет The Bell со ссылкой на источник, близкий к компании, представитель «Ростеха» подтвердил информацию. Сейчас фонд «Ростеха» проходит регистрацию. В будущем его объём может быть увеличет до 1 млрд рублей — решение будет принято по мере вхождения «Ростеха» в проекты, пояснил представитель компании. Госкорпорации создают венчурные фонды по распоряжению президента России Владимира Путина, которое он дал в июне 2017 года. Поручение касалось «Ростеха», «Росатома», Роскосмоса, Объединенной авиастроительной корпорации (ОАК) и Объединенной судостроительной корпорации (ОСК). «Ростех» последним объявил о своих планах. «Росатом» планирует вложить в стартапы 6 млрд рублей, компанию интересуют проекты, которые можно будет интегрировать в её производственный процесс. Роскосмос готовится запустить венчурный фонд к 1 апреля 2018 года в партнёрстве с РВК и «ВЭБ Инновациями». По данным «Ведомостей», объём фонда составит 3 млрд рублей. ОСК и ОАК планируют вложить в стартапы по 500 млн и 300 млн рублей соответственно. \\#новость #инвестиции "
}